fancy_text/__init__.py
fancy_text/main.py
you_are_gay-0.2.0.dist-info/licenses/LICENSE
you_are_gay-0.2.0.dist-info/METADATA
you_are_gay-0.2.0.dist-info/WHEEL
you_are_gay-0.2.0.dist-info/entry_points.txt
you_are_gay-0.2.0.dist-info/top_level.txt
you_are_gay-0.2.0.dist-info/RECORD
