Metadata-Version: 2.4
Name: you-are-gay
Version: 0.2.0
Summary: A package that displays a name with 'IS GAY' in a fancy way in the terminal
Home-page: https://github.com/username/you-are-gay
Author: Claude User
Author-email: user@example.com
Classifier: Programming Language :: Python :: 3
Classifier: License :: OSI Approved :: MIT License
Classifier: Operating System :: OS Independent
Requires-Python: >=3.6
License-File: LICENSE
Dynamic: author
Dynamic: author-email
Dynamic: classifier
Dynamic: description
Dynamic: description-content-type
Dynamic: home-page
Dynamic: license-file
Dynamic: requires-python
Dynamic: summary
